[
    {
      "name": "NEET Preparation - 2023",
      "date": "27-11-2023",
      "score": "80",
      "correct": "15",
      "incorrect": "5",
      "status": "Completed",
      "no_of_questions": 20
    },
    {
      "name": "Chemistry Challenge - 2023",
      "date": "28-11-2023",
      "score": "75",
      "correct": "14",
      "incorrect": "6",
      "status": "Completed",
      "no_of_questions": 25
    },
    {
      "name": "Physics Prodigy - 2023",
      "date": "29-11-2023",
      "score": "90",
      "correct": "18",
      "incorrect": "2",
      "status": "Running",
      "no_of_questions": 30
    },
    {
      "name": "Math Mastery - 2023",
      "date": "30-11-2023",
      "score": "85",
      "correct": "16",
      "incorrect": "4",
      "status": "Running",
      "no_of_questions": 22
    },
    {
      "name": "Medical Marvel - 2023",
      "date": "01-12-2023",
      "score": "95",
      "correct": "20",
      "incorrect": "0",
      "status": "Completed",
      "no_of_questions": 18
    },
    {
      "name": "Engineering Excellence - 2023",
      "date": "02-12-2023",
      "score": "70",
      "correct": "12",
      "incorrect": "8",
      "status": "Completed",
      "no_of_questions": 15
    },
    {
      "name": "Science Sprint - 2023",
      "date": "03-12-2023",
      "score": "88",
      "correct": "17",
      "incorrect": "3",
      "status": "Running",
      "no_of_questions": 28
    },
    {
      "name": "Technology Triumph - 2023",
      "date": "04-12-2023",
      "score": "92",
      "correct": "19",
      "incorrect": "1",
      "status": "Running",
      "no_of_questions": 24
    },
    {
      "name": "General Genius - 2023",
      "date": "05-12-2023",
      "score": "78",
      "correct": "13",
      "incorrect": "7",
      "status": "Completed",
      "no_of_questions": 20
    },
    {
      "name": "Knowledge Knight - 2023",
      "date": "06-12-2023",
      "score": "87",
      "correct": "16",
      "incorrect": "4",
      "status": "Running",
      "no_of_questions": 26
    }
  ]
  