[
    {
        "id":1,
        "name":"MCQ, Single Correct",
        "type":"R"
    },
    {
        "id":2,
        "name":"Essay",
        "type":"E"
    },
    {
        "id":3,
        "name":"MCQ, Multiple Correct",
        "type":"C"
    },
    {
        "id":4,
        "name":"Short Answer",
        "type":"S"
    },
    {
        "id":5,
        "name":"NAT, Numerical Answer Type",
        "type":"N"
    },
    {
        "id":6,
        "name":"File Type",
        "type":"F"
    },
    {
        "id":7,
        "name":"Match Type",
        "type":"M"
    },
    {
        "id":8,
        "name":"Nested Type",
        "type":"T"
    },
    {
        "id":9,
        "name":"Gap Fill Type",
        "type":"G"
    },
    {
        "id":10,
        "name":"Audio Type",
        "type":"A"
    }
]