[
  {
    "id": 1,
    "title": "TNPSC Group I Preparation Tips",
    "items": [
      {
        "type": "Image",
        "title": "Syllabus Overview",
        "url": "https://example.com/images/group1_syllabus.jpg"
      },
      {
        "type": "Link",
        "title": "Previous Year Papers",
        "url": "https://example.com/links/group1_papers"
      }
    ]
  },
  {
    "id": 2,
    "title": "General Science Study Material",
    "items": [
      {
        "type": "Video",
        "title": "Science Basics for TNPSC",
        "url": "https://example.com/videos/science_basics.mp4"
      }
    ]
  },
  {
    "id": 3,
    "title": "Tamil Language Preparation",
    "items": [
      {
        "type": "Image",
        "title": "Tamil Grammar Essentials",
        "url": "https://example.com/images/tamil_grammar.jpg"
      },
      {
        "type": "Link",
        "title": "Top Resources for Tamil",
        "url": "https://example.com/links/tamil_resources"
      }
    ]
  },
  {
    "id": 4,
    "title": "History of Tamil Nadu",
    "items": [
      {
        "type": "Video",
        "title": "Important Dynasties Explained",
        "url": "https://example.com/videos/tn_history.mp4"
      }
    ]
  },
  {
    "id": 5,
    "title": "TNPSC Exam Day Guidelines",
    "items": [
      {
        "type": "Image",
        "title": "Checklist for Exam Day",
        "url": "https://example.com/images/exam_checklist.jpg"
      },
      {
        "type": "Link",
        "title": "Dos and Don'ts",
        "url": "https://example.com/links/exam_guidelines"
      }
    ]
  },
  {
		"id": 6,
		"title": "Aptitude and Mental Ability",
		"items": [
			{
				"type": "Video",
				"title": "Quick Mental Math Tips",
				"url": "https://example.com/videos/mental_math.mp4"
			},
			{
				"type": "Link",
				"title": "Practice Questions",
				"url": "https://example.com/links/aptitude_practice"
			},
			{
				"type": "Image",
				"title": "Formulas to Remember",
				"url": "https://example.com/images/formulas.jpg"
			},
			{
				"type": "Video",
				"title": "Solving Time and Work Problems",
				"url": "https://example.com/videos/time_work.mp4"
			}
		]
	},	
  {
    "id": 7,
    "title": "TNPSC Geography Insights",
    "items": [
      {
        "type": "Image",
        "title": "Maps and Diagrams",
        "url": "https://example.com/images/tn_geography.jpg"
      }
    ]
  },
  {
    "id": 8,
    "title": "Indian Polity for TNPSC",
    "items": [
      {
        "type": "Video",
        "title": "Constitution Highlights",
        "url": "https://example.com/videos/constitution.mp4"
      },
      {
        "type": "Link",
        "title": "Important Articles",
        "url": "https://example.com/links/polity_articles"
      }
    ]
  },
  {
    "id": 9,
    "title": "Mock Tests for TNPSC",
    "items": [
      {
        "type": "Link",
        "title": "Full-Length Mock Test",
        "url": "https://example.com/links/mock_test1"
      },
      {
        "type": "Image",
        "title": "Answer Key for Mock Test",
        "url": "https://example.com/images/mock_test_answers.jpg"
      }
    ]
  },
  {
    "id": 10,
    "title": "Current Affairs Updates",
    "items": [
      {
        "type": "Link",
        "title": "Latest Events Summary",
        "url": "https://example.com/links/current_affairs"
      },
      {
        "type": "Video",
        "title": "Monthly Current Affairs Recap",
        "url": "https://example.com/videos/current_affairs_recaps.mp4"
      }
    ]
  }
]
