[
  {
    "id": "rc_001",
    "title": "SAT Projection",
    "course_name": "SAT Prep",
    "total_score": 1310,
    "score_range": "400-1600",
    "metrics": {
      "english_avg": 640,
      "math_avg": 670,
      "max_section": 800,
      "total_assessments": 5,
      "last_updated": "Mar 22, 2026"
    },
    "sections": [
      {
        "id": "sec_01",
        "title": "Reading & Writing",
        "type": "scholastic",
        "groups": [
          {
            "id": "grp_01",
            "title": "Module Tests & Weekly Drills",
            "average_score": 640,
            "average_percentage": "80%",
            "items": [
              { "name": "SAT English Practice Test 1", "date": "10 Mar 2026", "score": 620, "max": 800, "percentage": "77.5%", "review_url": "#" },
              { "name": "Weekly Drill - English", "date": "15 Mar 2026", "score": 660, "max": 800, "percentage": "82.5%", "review_url": "#" }
            ]
          }
        ]
      },
      {
        "id": "sec_02",
        "title": "Mathematics",
        "type": "scholastic",
        "groups": [
          {
            "id": "grp_02",
            "title": "Module Tests & Weekly Drills",
            "average_score": 670,
            "average_percentage": "83.75%",
            "items": [
              { "name": "SAT Math Practice Test 1", "date": "11 Mar 2026", "score": 650, "max": 800, "percentage": "81.25%", "review_url": "#" },
              { "name": "Weekly Drill - Math", "date": "16 Mar 2026", "score": 690, "max": 800, "percentage": "86.25%", "review_url": "#" }
            ]
          }
        ]
      }
    ]
  }
]